<?xml version="1.0" encoding="utf-8" ?><dwsync><file name="ui-bg_diagonals-thick_20_666666_40x40.png" server="sftp.edc.org/courses.edtechleaders.org/" local="3443017121" remote="318763443835913633" Dst="-1" /><file name="ui-bg_dots-medium_30_0b58a2_4x4.png" server="sftp.edc.org/courses.edtechleaders.org/" local="3443017122" remote="318763443835913634" Dst="-1" /><file name="ui-bg_dots-small_30_a32d00_2x2.png" server="sftp.edc.org/courses.edtechleaders.org/" local="3443017122" remote="318763443835913634" Dst="-1" /><file name="ui-bg_flat_0_aaaaaa_40x100.png" server="sftp.edc.org/courses.edtechleaders.org/" local="3443017122" remote="318763443835913634" Dst="-1" /><file name="ui-bg_highlight-hard_40_6aaae7_1x100.png" server="sftp.edc.org/courses.edtechleaders.org/" local="3443017122" remote="318763443835913634" Dst="-1" /><file name="ui-bg_highlight-soft_40_2c75ce_1x100.png" server="sftp.edc.org/courses.edtechleaders.org/" local="3443017123" remote="318763443835913635" Dst="-1" /><file name="ui-bg_highlight-soft_50_2c75ce_1x100.png" server="sftp.edc.org/courses.edtechleaders.org/" local="3443017123" remote="318763443835913635" Dst="-1" /><file name="ui-bg_highlight-soft_50_538ed5_1x100.png" server="sftp.edc.org/courses.edtechleaders.org/" local="3443017123" remote="318763443835913635" Dst="-1" /><file name="ui-bg_inset-hard_20_d9d9d9_1x100.png" server="sftp.edc.org/courses.edtechleaders.org/" local="3443017123" remote="318763443835913635" Dst="-1" /><file name="ui-icons_00498f_256x240.png" server="sftp.edc.org/courses.edtechleaders.org/" local="3443017124" remote="318763443835913636" Dst="-1" /><file name="ui-icons_9ccdfc_256x240.png" server="sftp.edc.org/courses.edtechleaders.org/" local="3443017124" remote="318763443835913636" Dst="-1" /><file name="ui-icons_b2cfeb_256x240.png" server="sftp.edc.org/courses.edtechleaders.org/" local="3443017124" remote="318763443835913636" Dst="-1" /><file name="ui-icons_e9ebec_256x240.png" server="sftp.edc.org/courses.edtechleaders.org/" local="3443017124" remote="318763443835913636" Dst="-1" /><file name="ui-icons_ffffff_256x240.png" server="sftp.edc.org/courses.edtechleaders.org/" local="3443017125" remote="318763443835913637" Dst="-1" /></dwsync>